rocketlc/__init__.py
rocketlc/florida_review.py
rocketlc/next_space_flight.py
rocketlc/rocket_launch_live.py
rocketlc/space_schedulle_launch.py
rocketlc/tools_ssl.py
rocketlc-0.1.5.dist-info/LICENSE
rocketlc-0.1.5.dist-info/METADATA
rocketlc-0.1.5.dist-info/WHEEL
rocketlc-0.1.5.dist-info/top_level.txt
rocketlc-0.1.5.dist-info/RECORD
