Metadata-Version: 2.2
Name: rocketlc
Version: 0.1.5
Summary: Library for getting schedule launch rocket
Home-page: https://github.com/reinanbr/rocketlc
Author: Reinan Br
Author-email: slimchatuba@gmail.com
License: BSD v3
Keywords: rocket launch schedule
License-File: LICENSE
Requires-Dist: requests
Requires-Dist: mechanicalsoup
Requires-Dist: cssutils
Requires-Dist: bs4
Dynamic: author
Dynamic: author-email
Dynamic: description-content-type
Dynamic: home-page
Dynamic: keywords
Dynamic: license
Dynamic: requires-dist
Dynamic: summary
